moyanlib/Error.py
moyanlib/__init__.py
moyanlib/cache.py
moyanlib/decorators.py
moyanlib/jsons.py
moyanlib/logger.py
moyanlib/system.py
moyanlib/cli/__init__.py
moyanlib-1.5.1723545174.dist-info/METADATA
moyanlib-1.5.1723545174.dist-info/WHEEL
moyanlib-1.5.1723545174.dist-info/entry_points.txt
moyanlib-1.5.1723545174.dist-info/top_level.txt
moyanlib-1.5.1723545174.dist-info/RECORD
