Metadata-Version: 2.1
Name: moyanlib
Version: 1.5.1723545174
Summary: 莫颜的个人python函数包
Home-page: UNKNOWN
Author: MoYan
License: UNKNOWN
Platform: UNKNOWN
Classifier: Development Status :: 3 - Alpha
Classifier: Intended Audience :: Developers
Classifier: Topic :: Software Development :: Libraries
Classifier: License :: OSI Approved :: MIT License
Classifier: Programming Language :: Python :: 3
Requires-Dist: click
Requires-Dist: psutil
Requires-Dist: requests
